{"battle":[{"action":"ability_front","text":"ゆくぞ！　とうっ！","type":null,"md5":{"voice":"1127487e8c23c7e6ceba45358fbd246f"}},{"action":"union_wait","text":"集まれ！　ヒーローパワー！","type":null,"md5":{"voice":"497a6c553246e0658806f6ea763580d5"}},{"action":"union_start","text":"これがヒーローというものだ！","type":null,"md5":{"voice":"13e463699b233535bc3248dd79042e2e"}},{"action":"default_ability_attack","text":"せい！","type":null,"md5":{"voice":"6b4290f608e55524b315b1cd1fe2583e"}},{"action":"default_ability_special","text":"はあ！","type":null,"md5":{"voice":"b547011b6a39e1cd7f537f0562a764f5"}},{"action":"default_ability_burst","text":"とう！","type":null,"md5":{"voice":"c3e3b34465eb839748b507e4840b0cbc"}},{"action":"default_ability_remote","text":"チェスト！","type":null,"md5":{"voice":"9a4cfb890629f9442f71e60dd52f12d4"}},{"action":"default_ability_yell_buff","text":"諦めてはダメだ！","type":null,"md5":{"voice":"4be40d498a580478677d1337c6c1f0f5"}},{"action":"default_ability_yell_debuff","text":"許さん！","type":null,"md5":{"voice":"3ec6a9f25c0a456be7a45722ce4fee1c"}},{"action":"stun","text":"ぐわぁ！　や・ら・れ・た〜","type":null,"md5":{"voice":"ae72a9f55e3f7eaa38e86cff1d06be2e"}}],"mypage":[{"action":"mypage","text":"かかってくるがよい！　アストルムファイブ！","type":null,"md5":{"voice":"4f4a7d36a5678511ed62bedd8e959639"}},{"action":"mypage","text":"そうか、私が怪人役ということか……","type":null,"md5":{"voice":"8a796e173ca73aae4baaaab393f04c09"}},{"action":"mypage","text":"ふっ……ふふふ……","type":null,"md5":{"voice":"84ff47e5e398222666a2fe969be61243"}},{"action":"mypage","text":"貴様ら……ヒーローの風上にもおけん！","type":null,"md5":{"voice":"8f76ca3633612c978e112245ad36611a"}},{"action":"mypage","text":"少年はさがっていろ。","type":"dearUp","md5":{"voice":"3d423725431cb88a93ae85e3d1f89010"}},{"action":"mypage","text":"五分前行動とは感心だな。","type":null,"md5":{"voice":"009cc96851c3f325c3c79c70634a853c"}},{"action":"mypage","text":"実は怪人役に欠員が出てしまったんだ。","type":null,"md5":{"voice":"a299299a3b990c5e1e11dd851ebe020f"}},{"action":"mypage","text":"大丈夫、少年は私が見込んだ男だ。","type":null,"md5":{"voice":"6889e3e87bbbae7cfca1abf6ebe0ac29"}},{"action":"mypage","text":"君には、怪人になってもらう。","type":null,"md5":{"voice":"53e75e76a69d468c583305ed4401f3c7"}},{"action":"mypage","text":"君以外に適任はいないんだ。頼む！","type":"dearUp","md5":{"voice":"0e81fb47e2e3460b012a97c2d7ba2794"}}],"quest":[{"action":"quest_default","text":"さがっていろ、少年。","type":"dearUp","md5":{"voice":"1c1a5043a250dbb61e01230195f29592"}},{"action":"quest_default","text":"さぁ、来るがいい！　怪人よ！","type":"dearUp","md5":{"voice":"83fb7a94fba26f2f3f0a280c0b2c12bd"}},{"action":"quest_default","text":"悪の気が満ちている……\n油断するな、少年。","type":"dearUp","md5":{"voice":"b46adaf01d53916a8bfed30fd0832421"}},{"action":"quest_default","text":"ヒーローとは何か、その身に刻み込んでくれる！","type":"dearUp","md5":{"voice":"79f8e93fc61b7972908516bba8c855f6"}},{"action":"quest_default","text":"少し休むか、少年？","type":"dearUp","md5":{"voice":"bb30730e6ee5dfc0586c2dbf40b63afe"}}],"enhance":[{"action":"raise_after","text":"良い汗をかいた……","type":null,"md5":{"voice":"1bd3c0e53f68440e40484f536d378c7b"}},{"action":"raise_coup_after","text":"努力は決して裏切らない！","type":null,"md5":{"voice":"dba92708255395f1da05cee32d716603"}},{"action":"evolution_after","text":"頼みがある、少年。","type":null,"md5":{"voice":"f1f0b2e78fa5d58fd90567d9cf4bb5fe"}},{"action":"limitbreak_after","text":"感謝しているぞ、少年。","type":null,"md5":{"voice":"0fd4d8f072e64326cf28080700a1e9fd"}}],"other":[{"action":"card_get","text":"……何者！？","type":null,"md5":{"voice":"9bb32f4b55ff82d1afe0c59e348e6f9d"}},{"action":"card_get","text":"アストルムファイブだと！？","type":null,"md5":{"voice":"3efea45ae8976f09ee49406d7edc82fe"}},{"action":"card_get","text":"ヒーローの風上にもおけんな。","type":null,"md5":{"voice":"0f332f31b0267a07dee20efd98e78cca"}}],"_hash":"676a4cd2e2e01f9dba5b00a73f7de862"}