{"battle":[{"action":"ability_front","text":"決める！","type":null,"md5":{"voice":"5d7ef88f4ffd0c21ad0ec143c08ccd44"}},{"action":"ability_back","text":"さあ、いまがチャンスよ！","type":null,"md5":{"voice":"4fc7db31169f1e4981d280d7c49307b8"}},{"action":"union_wait","text":"少し時間を作って！","type":null,"md5":{"voice":"b0184babc2b8db6d7bb187b3f054aa3b"}},{"action":"union_start","text":"私に任せて！","type":null,"md5":{"voice":"0d19fd9c76b0d2e569210aaecc002685"}},{"action":"default_ability_attack","text":"はっ！","type":null,"md5":{"voice":"96a660091ed12000036fd91bdc8308db"}},{"action":"default_ability_special","text":"行くわよ！","type":null,"md5":{"voice":"06a9e96317845dc41b5326133d1640db"}},{"action":"default_ability_burst","text":"てやっ！","type":null,"md5":{"voice":"53926c625a6feadcb8b2b0c27d8afa35"}},{"action":"default_ability_remote","text":"手伝うわ！","type":null,"md5":{"voice":"8035eb283b61738f58ff1eca408df4e0"}},{"action":"default_ability_yell_buff","text":"任せたからね！","type":null,"md5":{"voice":"89f3101dda519a8cae6706c41fc1f632"}},{"action":"default_ability_yell_debuff","text":"今よっ！","type":null,"md5":{"voice":"7165376701e2be86fa527db571667e51"}},{"action":"stun","text":"や、やだぁ……！","type":null,"md5":{"voice":"8d2aa0f5da242ae28d32d654cd38aeb5"}}],"mypage":[{"action":"mypage","text":"ちゃんと状況を見て、\n一番効果的なアイテムを使うのよ！","type":null,"md5":{"voice":"94319ea9f8fed469c438c63463245da3"}},{"action":"mypage","text":"戦闘全体の金銭効率をきちんと計算\nしなさい！","type":null,"md5":{"voice":"601044102be06e6b14e90e2f0b6c0a36"}},{"action":"mypage","text":"目先の事だけ考えてちゃダメ。\nねえ、聞いてるの？","type":null,"md5":{"voice":"8f46b30fc9dd684cc5ed04df7e52e73a"}},{"action":"mypage","text":"私が言ったことは守っているよう\nだけど、それだけじゃダメよ","type":"dearUp","md5":{"voice":"92b23ac2f91eddabffba55393560051c"}},{"action":"mypage","text":"強化アイテムを使うことは覚えた\nのね。でも使いどころも考えて","type":null,"md5":{"voice":"709abf233f14ddbf6544f53e325196ec"}},{"action":"mypage","text":"それ、そこのケーキ屋さんの箱？\nなんで隠すのよ","type":null,"md5":{"voice":"5bc383eca8ace0fea379580a9425bba6"}},{"action":"mypage","text":"私もサービス業を否定するつもりは\nないわ。立派な商売よ","type":null,"md5":{"voice":"7d68586bab8755d911ae5101ccbb4cc2"}},{"action":"mypage","text":"ここのカフェよりあっちのケーキ屋\nさんの方が安いわよ？","type":"dearUp","md5":{"voice":"2bf6c16a898d3fbff248a7e7283dcb36"}},{"action":"mypage","text":"ケーキも自分で作れば……ううん、\n量が少ないと微妙かしら？","type":null,"md5":{"voice":"2e3e831734038e50300233cce71d3905"}},{"action":"mypage","text":"ざっと見ただけで原価は分かるわ。\n人件費や諸費も含めてね","type":null,"md5":{"voice":"bfc46fe66f77368c5337c2610683ef1e"}}],"quest":[{"action":"quest_default","text":"金銭効率もいい感じね！\nこのままで行きましょう","type":"dearUp","md5":{"voice":"62aaeb7ebc23eaa1e31cd692f631f7b4"}},{"action":"quest_default","text":"こら、そのアイテムの使い所は\nここじゃないったら！","type":"dearUp","md5":{"voice":"c79f2f22dcf9333f069f3bb43c1890bb"}},{"action":"quest_default","text":"次の手は何がいいと思う？\n見ててあげるからやってみて！","type":"dearUp","md5":{"voice":"570cd25dace3a9c5004bcdd9e9029e88"}},{"action":"quest_default","text":"その辺に転がっている物だって\n集めて大金になる事もあるわ","type":"dearUp","md5":{"voice":"1fdd012b30beeb02d12c39ebb0c2a5e5"}},{"action":"quest_default","text":"疲れてきたなら休憩しましょ\n効率が落ちたら意味ないわ","type":"dearUp","md5":{"voice":"f045a1da3e028d3b21b09f52c642e452"}}],"enhance":[{"action":"raise_after","text":"一歩一歩の積み重ねが大切ね","type":null,"md5":{"voice":"30806f52fc79a71ab4d58f8e790f8a1f"}},{"action":"raise_coup_after","text":"すごい！　予想外の成果が出たわ！","type":null,"md5":{"voice":"848478463773ec39ba17ac0b4557f12e"}},{"action":"evolution_after","text":"もっともっと頑張れるはずよ！","type":null,"md5":{"voice":"64b1dc0a0e3c021fd188dcd7f544edc9"}},{"action":"limitbreak_after","text":"私にここまでの力があったの？","type":null,"md5":{"voice":"10661f80b3bcab27e3a47f554ac3cd71"}}],"other":[{"action":"card_get","text":"時間がもったいないわ。さっさと行きましょ","type":null,"md5":{"voice":"30e1b1b7dca72dfee63ebda9e06251e1"}},{"action":"card_get","text":"金銭効率の計算の仕方、教えてあげる！","type":null,"md5":{"voice":"414de90a8a9b7e50dacd026ca5ee6a50"}},{"action":"card_get","text":"ちゃんと一人で勝てるか見てあげるわ","type":null,"md5":{"voice":"22b8a317f13daa1040bdd7acaf5d33b9"}}],"_hash":"676a4cd2e2e01f9dba5b00a73f7de862"}