{"battle":[{"action":"ability_front","text":"終幕だ！","type":null,"md5":{"voice":"83178d7da65165a1ca6f20ce3e20b4c7"}},{"action":"ability_back","text":"私に続けっ！","type":null,"md5":{"voice":"d4fa225929b4b4097b05f13c7ada2e48"}},{"action":"union_wait","text":"対象を殲滅する","type":null,"md5":{"voice":"a54dce84f69f1ae9129806ddbf9e08b2"}},{"action":"union_start","text":"わが祖国のために！","type":null,"md5":{"voice":"ad75c44d0697ea0ae7be7ccbc4a3ecc9"}},{"action":"default_ability_attack","text":"はあっ！","type":null,"md5":{"voice":"b00eb66bf06847955c8a1372867d3182"}},{"action":"default_ability_special","text":"終わりだ！","type":null,"md5":{"voice":"3723173f11c1b353cf4bc1499b69664a"}},{"action":"default_ability_burst","text":"ていっ！","type":null,"md5":{"voice":"adec2a71805538cc211c5f546fdf5d60"}},{"action":"default_ability_remote","text":"かかったな！","type":null,"md5":{"voice":"e18cba7b8d9975e87ea186d9b291e659"}},{"action":"default_ability_yell_buff","text":"サポートする！","type":null,"md5":{"voice":"271820b385091d14af7543a57e4a5b89"}},{"action":"default_ability_yell_debuff","text":"どうした！　来い！","type":null,"md5":{"voice":"dd98ca6908d6e26f38c0a64deaf85a09"}},{"action":"stun","text":"まさか……この私が！？","type":null,"md5":{"voice":"90cbb0063eab8d5cb40e4fb73556ef42"}}],"mypage":[{"action":"mypage","text":"弱点をスピードで補う。悪くない発想だ。","type":null,"md5":{"voice":"e4ec874b16776b9c58f0c2b6e1140d43"}},{"action":"mypage","text":"祖国のため、弱点を克服してみせる！","type":null,"md5":{"voice":"857dac7fb8d0e45ecd17b9210b83582c"}},{"action":"mypage","text":"だから頭を撫でるなと言っている！","type":"dearUp","md5":{"voice":"b722fe10003926948b8ab152470de65c"}},{"action":"mypage","text":"足の長さでは負けていない！","type":null,"md5":{"voice":"d9a84ff449bd013dc0473ca7d832f036"}},{"action":"mypage","text":"優勝商品、なんとしても手に入れるぞ！","type":null,"md5":{"voice":"86cf91ade2b9bb7083f94ba89423307b"}},{"action":"mypage","text":"カラオケなどというものに、興味はない。","type":null,"md5":{"voice":"fca39a5fb8858a7be974ff7cb6455f4f"}},{"action":"mypage","text":"私には、調査任務があるのだ","type":null,"md5":{"voice":"40ad75ee40a647d3ff0dc75956e4721b"}},{"action":"mypage","text":"その土地の食べ物を、調査していたのだ！","type":null,"md5":{"voice":"efcacccf316543fdd378712ae54c66a1"}},{"action":"mypage","text":"はむ……ふふふ、やはりくるくるキャンディに限るな～","type":"dearUp","md5":{"voice":"ff01f45a380a655ab3b6b3ed74fdf399"}},{"action":"mypage","text":"菓子ならやらんぞー","type":null,"md5":{"voice":"ba8883884579c1fe3a8556e448ae1e0e"}}],"quest":[{"action":"quest_default","text":"背中は任せる。\nよろしく頼むぞ！","type":"dearUp","md5":{"voice":"bbb1b40c3372f289b8db88ff969ee4de"}},{"action":"quest_default","text":"私のスピードで、\n一気にかたをつけてやる！","type":"dearUp","md5":{"voice":"3f3da9707c119e18a6fd594e8833aed5"}},{"action":"quest_default","text":"安心しろ。貴公がピンチ\nのときは、私が助ける。","type":"dearUp","md5":{"voice":"c21ac6faa05a801aa2a00c521bf62994"}},{"action":"quest_default","text":"はむ……ん！\n菓子など食べていないぞ！","type":"dearUp","md5":{"voice":"f94805bc155d36a6b36220bb54139a67"}},{"action":"quest_default","text":"貴公と共に歩めること、\n嬉しく思っている。","type":"dearUp","md5":{"voice":"a4c43ada970701bb95c44ce5df618841"}}],"enhance":[{"action":"raise_after","text":"それでは、失礼する......","type":null,"md5":{"voice":"f7e6cc2d4f0d1b7139bab5ee51056961"}},{"action":"raise_coup_after","text":"ようやくわかってくれたようだな。","type":null,"md5":{"voice":"40f3c304c9a31118a9d708798df664a2"}},{"action":"evolution_after","text":"ドイツ軍人としての誇りが、私を強くする！","type":null,"md5":{"voice":"acc9af1928e4c88fbf6ff583ce4c6890"}},{"action":"limitbreak_after","text":"私は強くあらねばならぬのだ","type":null,"md5":{"voice":"abc3ceab65b72fc8341091004f46984d"}}],"other":[{"action":"card_get","text":"貴公には協力してもらわねばならん。","type":null,"md5":{"voice":"8efdb97688482adc6048f698e609e187"}},{"action":"card_get","text":"わが祖国のため、貴公にも協力願おう。","type":null,"md5":{"voice":"ab90cb609ae5402db8551daed2e016e3"}},{"action":"card_get","text":"……プリンセスナイトか。\nよかろう、共に戦おう。","type":null,"md5":{"voice":"5f43d197f9c33ab95ed793f4aebd9132"}}],"_hash":"676a4cd2e2e01f9dba5b00a73f7de862"}