{"battle":[{"action":"ability_front","text":"漲るッス！","type":null,"md5":{"voice":"ba9d07e9eceee407db7f3379f9bb000b"}},{"action":"ability_back","text":"いくッス！","type":null,"md5":{"voice":"451b2a28bce5f31aec5f8c8569d1ba1e"}},{"action":"union_wait","text":"絶対無敵！","type":null,"md5":{"voice":"31eb6963b7357c6647112bdee8debf81"}},{"action":"union_start","text":"タイガーファイター！！","type":null,"md5":{"voice":"a04a7a8f3bf1e36378315cd4529f9901"}},{"action":"default_ability_attack","text":"とうっ！","type":null,"md5":{"voice":"01f50162601001fd685ac22c4086af75"}},{"action":"default_ability_special","text":"ここだっ！","type":null,"md5":{"voice":"8268fbd985933977ebc37f2c88d0e45d"}},{"action":"default_ability_burst","text":"待てーっ！！","type":null,"md5":{"voice":"89547d0d91d19b15d201788bee3272a6"}},{"action":"default_ability_remote","text":"そーれっ！","type":null,"md5":{"voice":"353f51195f6ee357295b5d9178297551"}},{"action":"default_ability_yell_buff","text":"皆、根性ッス！！","type":null,"md5":{"voice":"6e1387f580a52a22c32c8780e86e9279"}},{"action":"default_ability_yell_debuff","text":"掛かって来～い！","type":null,"md5":{"voice":"3826f9c50280ac3e60f1a1dcf0358764"}},{"action":"stun","text":"なかなかやるッスね……","type":null,"md5":{"voice":"363c7d08f7cf8ac095e7cc93e4c5bd1a"}}],"mypage":[{"action":"mypage","text":"絶対無敵！　タイガーファイター!!","type":null,"md5":{"voice":"9b70a01fe9534900b869c4297a8841b1"}},{"action":"mypage","text":"これが伝説の友情パワーッスね!!","type":null,"md5":{"voice":"452b6ecd1e02509fcad5403b0450ba61"}},{"action":"mypage","text":"ししょー、ししょー♪","type":"dearUp","md5":{"voice":"44424e8492b08698000bddaa699be8e4"}},{"action":"mypage","text":"正真正銘のヒーローを目指すッス！","type":null,"md5":{"voice":"2d296aa7d37eb3d98cf7fc7ac4c5d5c3"}},{"action":"mypage","text":"強くなるために毎日筋トレしてるッス！","type":null,"md5":{"voice":"a573a7b1a3fcfbc11b2bc3e8f26e4bc8"}},{"action":"mypage","text":"遊園地の平和は自分が守るっス！","type":null,"md5":{"voice":"328aaac28663f41cdafc4a599d88ff06"}},{"action":"mypage","text":"ポイ捨てなんて、とんでもないッス！","type":null,"md5":{"voice":"2231041b651631f683db82beaebf8a62"}},{"action":"mypage","text":"遊園地でまで修行なんてスゴイッス!!","type":null,"md5":{"voice":"df4dd5d20749c1b6122b3acf4d275372"}},{"action":"mypage","text":"ヒーローの紋章、カッコイイッス～…！","type":null,"md5":{"voice":"43f294e8e1fe406efe5aa56ed119269a"}},{"action":"mypage","text":"アニキを見習って自分も修行するッス","type":"dearUp","md5":{"voice":"4e26666b47a21d4ab0811aab3f825392"}}],"quest":[{"action":"quest_default","text":"ししょー、ししょー♪\n……呼んでみただけッス♪","type":"dearUp","md5":{"voice":"317648bb5f69f2061cbdba0f9b93dc72"}},{"action":"quest_default","text":"最近腕とか逞しくなってきた\n気がするッス！　むん！","type":"dearUp","md5":{"voice":"65917da8cda36487b2c15d231f6448e8"}},{"action":"quest_default","text":"ししょーのお蔭で目覚めた力、\n正義の為に役立てるッス！！","type":"dearUp","md5":{"voice":"4932446e49443ba7c01b942eeef6ef79"}},{"action":"quest_default","text":"ヒーローの鉄則その１０ッ…\nなんで聞いてくれないんスか～","type":"dearUp","md5":{"voice":"29c8ef8312173dbaf0fb547f3fdf07fa"}},{"action":"quest_default","text":"タイガーファイターは\n絶対無敵、正義のヒーローッス","type":"dearUp","md5":{"voice":"bba5ad2684a1a96d80d1e963f56cb725"}}],"enhance":[{"action":"raise_after","text":"自分、頑張ったッス！","type":null,"md5":{"voice":"65a1ff6a54ee604794d9801837adc66e"}},{"action":"raise_coup_after","text":"ししょーっ！　褒めてほしいッス～！♪","type":null,"md5":{"voice":"d051dc3409d729cfb7021dd1bff79dd6"}},{"action":"evolution_after","text":"悪はタイガーファイターが許さないッス！","type":null,"md5":{"voice":"462763d30d1e4e8485301a5f84527de4"}},{"action":"limitbreak_after","text":"ししょーに一生ついていくッス！","type":null,"md5":{"voice":"316ee0188a87d4b0fd41378ca0c9466e"}}],"other":[{"action":"card_get","text":"悪を倒せと呼ばれてきたっス!!","type":null,"md5":{"voice":"2fcf52b916e667b70c01af6faee6d67b"}},{"action":"card_get","text":"タイガーファイターただいま参上！","type":null,"md5":{"voice":"033d434cb77b8f0b3518dbf26b7c9267"}},{"action":"card_get","text":"友情パワー、見せてやるッス！","type":null,"md5":{"voice":"b307f336d8bfd9c309be713a2ab378c2"}}],"_hash":"676a4cd2e2e01f9dba5b00a73f7de862"}